bookscrape/__init__.py
bookscrape/command_line.py
bookscrape/exceptions.py
bookscrape/loggers.py
bookscrape/scrapy.cfg
bookscrape/crawl/__init__.py
bookscrape/crawl/exporters.py
bookscrape/crawl/items.py
bookscrape/crawl/middlewares.py
bookscrape/crawl/pipelines.py
bookscrape/crawl/settings.py
bookscrape/crawl/spiders/__init__.py
bookscrape/crawl/spiders/bases.py
bookscrape/crawl/spiders/kissmanga.py
bookscrape/crawl/spiders/kissmanga_readcomics_base.py
bookscrape/crawl/spiders/readcomiconline.py
bookscrape-0.0.2b7.dist-info/DESCRIPTION.rst
bookscrape-0.0.2b7.dist-info/METADATA
bookscrape-0.0.2b7.dist-info/RECORD
bookscrape-0.0.2b7.dist-info/WHEEL
bookscrape-0.0.2b7.dist-info/entry_points.txt
bookscrape-0.0.2b7.dist-info/metadata.json
bookscrape-0.0.2b7.dist-info/top_level.txt
tests/__init__.py
tests/test_command_line.py
tests/test_exporters.py
tests/test_pipelines.py
