Metadata-Version: 2.0
Name: bookscrape
Version: 0.0.2b7
Summary: Scrape and build e-books from various websites
Home-page: https://github.com/clemfromspace/bookscrape
Author: UNKNOWN
Author-email: UNKNOWN
License: UNKNOWN
Platform: UNKNOWN
Requires-Dist: cfscrape (>=1.9.1)
Requires-Dist: logzero (==1.3.1)
Requires-Dist: Pillow (==5.0.0)
Requires-Dist: pycrypto (==2.6.1)
Requires-Dist: PyExecJS (==1.5.1)
Requires-Dist: python-dateutil (==2.6.1)
Requires-Dist: reportlab (==3.4.0)
Requires-Dist: Scrapy (==1.5.0)
